PythonWebShenduXuexiShiyongZhinanChuyi/README.md
PythonWebShenduXuexiShiyongZhinanChuyi/__init__.py
PythonWebShenduXuexiShiyongZhinanChuyi/__main__.py
PythonWebShenduXuexiShiyongZhinanChuyi/file.epub
PythonWebShenduXuexiShiyongZhinanChuyi/index.html
PythonWebShenduXuexiShiyongZhinanChuyi/css/__init__.py
PythonWebShenduXuexiShiyongZhinanChuyi/css/annotations.css
PythonWebShenduXuexiShiyongZhinanChuyi/css/main.css
PythonWebShenduXuexiShiyongZhinanChuyi/css/normalize.css
PythonWebShenduXuexiShiyongZhinanChuyi/css/popup.css
PythonWebShenduXuexiShiyongZhinanChuyi/font/__init__.py
PythonWebShenduXuexiShiyongZhinanChuyi/font/fontello.eot
PythonWebShenduXuexiShiyongZhinanChuyi/font/fontello.svg
PythonWebShenduXuexiShiyongZhinanChuyi/font/fontello.ttf
PythonWebShenduXuexiShiyongZhinanChuyi/font/fontello.woff
PythonWebShenduXuexiShiyongZhinanChuyi/img/__init__.py
PythonWebShenduXuexiShiyongZhinanChuyi/img/annotator-glyph-sprite.png
PythonWebShenduXuexiShiyongZhinanChuyi/img/annotator-icon-sprite.png
PythonWebShenduXuexiShiyongZhinanChuyi/img/apple-touch-icon.png
PythonWebShenduXuexiShiyongZhinanChuyi/img/cancelfullscreen.png
PythonWebShenduXuexiShiyongZhinanChuyi/img/close.png
PythonWebShenduXuexiShiyongZhinanChuyi/img/fullscreen.png
PythonWebShenduXuexiShiyongZhinanChuyi/img/loader.gif
PythonWebShenduXuexiShiyongZhinanChuyi/img/menu-icon.png
PythonWebShenduXuexiShiyongZhinanChuyi/img/save.png
PythonWebShenduXuexiShiyongZhinanChuyi/img/saved.png
PythonWebShenduXuexiShiyongZhinanChuyi/img/settings-s.png
PythonWebShenduXuexiShiyongZhinanChuyi/img/settings.png
PythonWebShenduXuexiShiyongZhinanChuyi/img/star.png
PythonWebShenduXuexiShiyongZhinanChuyi/js/__init__.py
PythonWebShenduXuexiShiyongZhinanChuyi/js/epub.js
PythonWebShenduXuexiShiyongZhinanChuyi/js/epub.min.js
PythonWebShenduXuexiShiyongZhinanChuyi/js/epub.min.map
PythonWebShenduXuexiShiyongZhinanChuyi/js/hooks.min.js
PythonWebShenduXuexiShiyongZhinanChuyi/js/hooks.min.map
python_web_shendu_xuexi_shiyong_zhinan_chuyi-2024.3.6.0.dist-info/METADATA
python_web_shendu_xuexi_shiyong_zhinan_chuyi-2024.3.6.0.dist-info/WHEEL
python_web_shendu_xuexi_shiyong_zhinan_chuyi-2024.3.6.0.dist-info/entry_points.txt
python_web_shendu_xuexi_shiyong_zhinan_chuyi-2024.3.6.0.dist-info/top_level.txt
python_web_shendu_xuexi_shiyong_zhinan_chuyi-2024.3.6.0.dist-info/RECORD
